MANIFEST.in
README.rst
setup.py
coffer/__init__.py
coffer/cli.py
coffer/client.py
coffer/server.py
coffer/webapp.py
coffer/zeroconf_utils.py
coffer.egg-info/PKG-INFO
coffer.egg-info/SOURCES.txt
coffer.egg-info/dependency_links.txt
coffer.egg-info/entry_points.txt
coffer.egg-info/not-zip-safe
coffer.egg-info/requires.txt
coffer.egg-info/top_level.txt