Metadata-Version: 1.1
Name: coffer
Version: 0.3
Summary: Easily send and receive files in your LAN. Without ever typing an IP address.
Home-page: UNKNOWN
Author: boyska
Author-email: piuttosto@logorroici.org
License: GPL3
Platform: UNKNOWN
Classifier: Framework :: Flask
Classifier: License :: OSI Approved :: GNU General Public License v3 or later (GPLv3+)
Classifier: Operating System :: POSIX :: Linux
Classifier: Programming Language :: Python :: 2
